[
  {
    "profile_id": "5a4cfa69-178e-45f8-8b82-0bc8a9b5a819",
    "name": {
      "value": "Priya Patel",
      "confidence": "HIGH",
      "provenance": {
        "source_type": "CSV",
        "source_file": "data\\input\\csv\\recruiter_export_2.csv",
        "original_value": "Priya Patel",
        "transformation": null,
        "transformed_value": null,
        "timestamp": "2026-06-30T18:57:05.208426"
      }
    },
    "email": {
      "value": "priya.patel@example.com",
      "confidence": "HIGH",
      "provenance": {
        "source_type": "CSV",
        "source_file": "data\\input\\csv\\recruiter_export_2.csv",
        "original_value": "priya.patel@example.com",
        "transformation": "lowercase+trim",
        "transformed_value": "priya.patel@example.com",
        "timestamp": "2026-06-30T18:57:05.208570"
      }
    },
    "contact": {
      "email": {
        "value": "priya.patel@example.com",
        "confidence": "HIGH",
        "provenance": {
          "source_type": "CSV",
          "source_file": "data\\input\\csv\\recruiter_export_2.csv",
          "original_value": "priya.patel@example.com",
          "transformation": "lowercase+trim",
          "transformed_value": "priya.patel@example.com",
          "timestamp": "2026-06-30T18:57:05.208570"
        }
      },
      "phone": {
        "value": "+14085550166",
        "confidence": "HIGH",
        "provenance": {
          "source_type": "CSV",
          "source_file": "data\\input\\csv\\recruiter_export_2.csv",
          "original_value": "408-555-0166",
          "transformation": "E.164 normalize",
          "transformed_value": "+14085550166",
          "timestamp": "2026-06-30T18:57:05.212318"
        }
      },
      "linkedin": null,
      "address": null
    },
    "skills": [
      {
        "value": "Go",
        "confidence": "HIGH",
        "provenance": {
          "source_type": "CSV",
          "source_file": "data\\input\\csv\\recruiter_export_2.csv",
          "original_value": "Go",
          "transformation": null,
          "transformed_value": null,
          "timestamp": "2026-06-30T18:57:05.212470"
        }
      },
      {
        "value": "gRPC",
        "confidence": "HIGH",
        "provenance": {
          "source_type": "CSV",
          "source_file": "data\\input\\csv\\recruiter_export_2.csv",
          "original_value": "gRPC",
          "transformation": null,
          "transformed_value": null,
          "timestamp": "2026-06-30T18:57:05.212476"
        }
      },
      {
        "value": "PostgreSQL",
        "confidence": "HIGH",
        "provenance": {
          "source_type": "CSV",
          "source_file": "data\\input\\csv\\recruiter_export_2.csv",
          "original_value": "PostgreSQL",
          "transformation": null,
          "transformed_value": null,
          "timestamp": "2026-06-30T18:57:05.212478"
        }
      }
    ],
    "experience": [],
    "education": [],
    "source_files": [
      "data\\input\\csv\\recruiter_export_2.csv"
    ],
    "processing_timestamp": "2026-06-30T18:57:05.212581",
    "total_confidence": 1.0,
    "merge_notes": [],
    "current_company": {
      "value": "IBM",
      "confidence": "HIGH",
      "provenance": {
        "source_type": "CSV",
        "source_file": "data\\input\\csv\\recruiter_export_2.csv",
        "original_value": "IBM",
        "transformation": null,
        "transformed_value": null,
        "timestamp": "2026-06-30T18:57:05.212486"
      }
    },
    "years_of_experience": {
      "value": 6.0,
      "confidence": "HIGH",
      "provenance": {
        "source_type": "CSV",
        "source_file": "data\\input\\csv\\recruiter_export_2.csv",
        "original_value": "6",
        "transformation": "to_float",
        "transformed_value": 6.0,
        "timestamp": "2026-06-30T18:57:05.212525"
      }
    },
    "job_titles": [
      {
        "value": "Platform Engineer",
        "confidence": "HIGH",
        "provenance": {
          "source_type": "CSV",
          "source_file": "data\\input\\csv\\recruiter_export_2.csv",
          "original_value": "Platform Engineer",
          "transformation": null,
          "transformed_value": null,
          "timestamp": "2026-06-30T18:57:05.212483"
        }
      }
    ],
    "certifications": [],
    "origin": "CSV"
  },
  {
    "profile_id": "6fd982e3-aa48-4da8-b54f-f991cd6e8287",
    "name": {
      "value": "Tom Becker",
      "confidence": "HIGH",
      "provenance": {
        "source_type": "CSV",
        "source_file": "data\\input\\csv\\recruiter_export_2.csv",
        "original_value": "Tom Becker",
        "transformation": null,
        "transformed_value": null,
        "timestamp": "2026-06-30T18:57:05.212873"
      }
    },
    "email": {
      "value": "tom.becker@example.com",
      "confidence": "HIGH",
      "provenance": {
        "source_type": "CSV",
        "source_file": "data\\input\\csv\\recruiter_export_2.csv",
        "original_value": "tom.becker@example.com",
        "transformation": "lowercase+trim",
        "transformed_value": "tom.becker@example.com",
        "timestamp": "2026-06-30T18:57:05.213051"
      }
    },
    "contact": {
      "email": {
        "value": "tom.becker@example.com",
        "confidence": "HIGH",
        "provenance": {
          "source_type": "CSV",
          "source_file": "data\\input\\csv\\recruiter_export_2.csv",
          "original_value": "tom.becker@example.com",
          "transformation": "lowercase+trim",
          "transformed_value": "tom.becker@example.com",
          "timestamp": "2026-06-30T18:57:05.213051"
        }
      },
      "phone": {
        "value": "+13125550121",
        "confidence": "HIGH",
        "provenance": {
          "source_type": "CSV",
          "source_file": "data\\input\\csv\\recruiter_export_2.csv",
          "original_value": "312-555-0121",
          "transformation": "E.164 normalize",
          "transformed_value": "+13125550121",
          "timestamp": "2026-06-30T18:57:05.213180"
        }
      },
      "linkedin": null,
      "address": null
    },
    "skills": [
      {
        "value": "C++",
        "confidence": "HIGH",
        "provenance": {
          "source_type": "CSV",
          "source_file": "data\\input\\csv\\recruiter_export_2.csv",
          "original_value": "C++",
          "transformation": null,
          "transformed_value": null,
          "timestamp": "2026-06-30T18:57:05.213265"
        }
      },
      {
        "value": "Linux",
        "confidence": "HIGH",
        "provenance": {
          "source_type": "CSV",
          "source_file": "data\\input\\csv\\recruiter_export_2.csv",
          "original_value": "Linux",
          "transformation": null,
          "transformed_value": null,
          "timestamp": "2026-06-30T18:57:05.213268"
        }
      },
      {
        "value": "Embedded Systems",
        "confidence": "HIGH",
        "provenance": {
          "source_type": "CSV",
          "source_file": "data\\input\\csv\\recruiter_export_2.csv",
          "original_value": "Embedded Systems",
          "transformation": null,
          "transformed_value": null,
          "timestamp": "2026-06-30T18:57:05.213279"
        }
      }
    ],
    "experience": [],
    "education": [],
    "source_files": [
      "data\\input\\csv\\recruiter_export_2.csv"
    ],
    "processing_timestamp": "2026-06-30T18:57:05.213323",
    "total_confidence": 1.0,
    "merge_notes": [],
    "current_company": {
      "value": "Apple",
      "confidence": "HIGH",
      "provenance": {
        "source_type": "CSV",
        "source_file": "data\\input\\csv\\recruiter_export_2.csv",
        "original_value": "Apple",
        "transformation": null,
        "transformed_value": null,
        "timestamp": "2026-06-30T18:57:05.213286"
      }
    },
    "years_of_experience": {
      "value": 9.0,
      "confidence": "HIGH",
      "provenance": {
        "source_type": "CSV",
        "source_file": "data\\input\\csv\\recruiter_export_2.csv",
        "original_value": "9",
        "transformation": "to_float",
        "transformed_value": 9.0,
        "timestamp": "2026-06-30T18:57:05.213292"
      }
    },
    "job_titles": [
      {
        "value": "Systems Engineer",
        "confidence": "HIGH",
        "provenance": {
          "source_type": "CSV",
          "source_file": "data\\input\\csv\\recruiter_export_2.csv",
          "original_value": "Systems Engineer",
          "transformation": null,
          "transformed_value": null,
          "timestamp": "2026-06-30T18:57:05.213283"
        }
      }
    ],
    "certifications": [],
    "origin": "CSV"
  },
  {
    "profile_id": "49895727-f6bc-4435-b4c5-6c3664275f21",
    "name": {
      "value": "Jane Doe",
      "confidence": "HIGH",
      "provenance": {
        "source_type": "MERGED",
        "source_file": "merged",
        "original_value": [
          "Jane Doe",
          "Jane Doe"
        ],
        "transformation": "agreement_merge",
        "transformed_value": null,
        "timestamp": "2026-06-30T18:57:05.535283"
      }
    },
    "email": {
      "value": "jane.doe@example.com",
      "confidence": "HIGH",
      "provenance": {
        "source_type": "MERGED",
        "source_file": "merged",
        "original_value": [
          "jane.doe@example.com",
          "jane.doe@example.com"
        ],
        "transformation": "agreement_merge",
        "transformed_value": null,
        "timestamp": "2026-06-30T18:57:05.535289"
      }
    },
    "contact": {
      "email": {
        "value": "jane.doe@example.com",
        "confidence": "HIGH",
        "provenance": {
          "source_type": "MERGED",
          "source_file": "merged",
          "original_value": [
            "jane.doe@example.com",
            "jane.doe@example.com"
          ],
          "transformation": "agreement_merge",
          "transformed_value": null,
          "timestamp": "2026-06-30T18:57:05.535292"
        }
      },
      "phone": {
        "value": "+14155550182",
        "confidence": "HIGH",
        "provenance": {
          "source_type": "MERGED",
          "source_file": "merged",
          "original_value": [
            "+14155550182",
            "+14155550182"
          ],
          "transformation": "agreement_merge",
          "transformed_value": null,
          "timestamp": "2026-06-30T18:57:05.535294"
        }
      },
      "linkedin": {
        "value": "linkedin.com/in/janedoe",
        "confidence": "HIGH",
        "provenance": {
          "source_type": "MERGED",
          "source_file": "merged",
          "original_value": [
            "linkedin.com/in/janedoe",
            "linkedin.com/in/janedoe"
          ],
          "transformation": "agreement_merge",
          "transformed_value": null,
          "timestamp": "2026-06-30T18:57:05.535296"
        }
      },
      "address": null
    },
    "skills": [
      {
        "value": "Python",
        "confidence": "HIGH",
        "provenance": {
          "source_type": "CSV",
          "source_file": "data\\input\\csv\\recruiter_export_1.csv",
          "original_value": "Python",
          "transformation": null,
          "transformed_value": null,
          "timestamp": "2026-06-30T18:57:05.213566"
        }
      },
      {
        "value": "Django",
        "confidence": "HIGH",
        "provenance": {
          "source_type": "CSV",
          "source_file": "data\\input\\csv\\recruiter_export_1.csv",
          "original_value": "Django",
          "transformation": null,
          "transformed_value": null,
          "timestamp": "2026-06-30T18:57:05.213568"
        }
      },
      {
        "value": "AWS",
        "confidence": "HIGH",
        "provenance": {
          "source_type": "CSV",
          "source_file": "data\\input\\csv\\recruiter_export_1.csv",
          "original_value": "AWS",
          "transformation": null,
          "transformed_value": null,
          "timestamp": "2026-06-30T18:57:05.213569"
        }
      },
      {
        "value": "Docker",
        "confidence": "HIGH",
        "provenance": {
          "source_type": "CSV",
          "source_file": "data\\input\\csv\\recruiter_export_1.csv",
          "original_value": "Docker",
          "transformation": null,
          "transformed_value": null,
          "timestamp": "2026-06-30T18:57:05.213571"
        }
      },
      {
        "value": "React",
        "confidence": "MEDIUM",
        "provenance": {
          "source_type": "RESUME_PDF",
          "source_file": "data\\input\\resumes\\jane_doe_resume.pdf",
          "original_value": "React",
          "transformation": "taxonomy_map",
          "transformed_value": "React",
          "timestamp": "2026-06-30T18:57:05.254695"
        }
      },
      {
        "value": "Kubernetes",
        "confidence": "MEDIUM",
        "provenance": {
          "source_type": "RESUME_PDF",
          "source_file": "data\\input\\resumes\\jane_doe_resume.pdf",
          "original_value": "Kubernetes",
          "transformation": "taxonomy_map",
          "transformed_value": "Kubernetes",
          "timestamp": "2026-06-30T18:57:05.254700"
        }
      },
      {
        "value": "PostgreSQL",
        "confidence": "MEDIUM",
        "provenance": {
          "source_type": "RESUME_PDF",
          "source_file": "data\\input\\resumes\\jane_doe_resume.pdf",
          "original_value": "PostgreSQL",
          "transformation": "taxonomy_map",
          "transformed_value": "PostgreSQL",
          "timestamp": "2026-06-30T18:57:05.254702"
        }
      },
      {
        "value": "Microservices",
        "confidence": "MEDIUM",
        "provenance": {
          "source_type": "RESUME_PDF",
          "source_file": "data\\input\\resumes\\jane_doe_resume.pdf",
          "original_value": "Microservices",
          "transformation": "taxonomy_map",
          "transformed_value": "Microservices",
          "timestamp": "2026-06-30T18:57:05.254703"
        }
      }
    ],
    "experience": [
      {
        "company": {
          "value": "Google",
          "confidence": "MEDIUM",
          "provenance": {
            "source_type": "RESUME_PDF",
            "source_file": "data\\input\\resumes\\jane_doe_resume.pdf",
            "original_value": "Google",
            "transformation": null,
            "transformed_value": null,
            "timestamp": "2026-06-30T18:57:05.522772"
          }
        },
        "title": {
          "value": "Senior Software Engineer",
          "confidence": "MEDIUM",
          "provenance": {
            "source_type": "RESUME_PDF",
            "source_file": "data\\input\\resumes\\jane_doe_resume.pdf",
            "original_value": "Senior Software Engineer",
            "transformation": null,
            "transformed_value": null,
            "timestamp": "2026-06-30T18:57:05.522774"
          }
        },
        "start_date": {
          "value": "2021-01",
          "confidence": "MEDIUM",
          "provenance": {
            "source_type": "RESUME_PDF",
            "source_file": "data\\input\\resumes\\jane_doe_resume.pdf",
            "original_value": "Jan 2021",
            "transformation": "date_normalize",
            "transformed_value": "2021-01",
            "timestamp": "2026-06-30T18:57:05.522766"
          }
        },
        "end_date": {
          "value": "PRESENT",
          "confidence": "MEDIUM",
          "provenance": {
            "source_type": "RESUME_PDF",
            "source_file": "data\\input\\resumes\\jane_doe_resume.pdf",
            "original_value": "Present",
            "transformation": "date_normalize",
            "transformed_value": "PRESENT",
            "timestamp": "2026-06-30T18:57:05.522770"
          }
        },
        "description": {
          "value": "Jan 2021 - Present\nLed backend services migration to microservices architecture using Docker and Kubernetes.\nSoftware Engineer at Salesforce\nJun 2017 - Dec 2020\nBuilt internal tools using Python and Django, improved deployment pipeline with AWS.",
          "confidence": "LOW",
          "provenance": {
            "source_type": "RESUME_PDF",
            "source_file": "data\\input\\resumes\\jane_doe_resume.pdf",
            "original_value": "Jan 2021 - Present\nLed backend services migration to microservices architecture using Docker and Kubernetes.\nSoftware Engineer at Salesforce\nJun 2017 - Dec 2020\nBuilt internal tools using Python and Django, improved deployment pipeline with AWS.",
            "transformation": null,
            "transformed_value": null,
            "timestamp": "2026-06-30T18:57:05.522776"
          }
        },
        "current": true
      }
    ],
    "education": [
      {
        "institution": {
          "value": "Stanford University",
          "confidence": "MEDIUM",
          "provenance": {
            "source_type": "RESUME_PDF",
            "source_file": "data\\input\\resumes\\jane_doe_resume.pdf",
            "original_value": "Stanford University",
            "transformation": null,
            "transformed_value": null,
            "timestamp": "2026-06-30T18:57:05.522780"
          }
        },
        "degree": {
          "value": "Bachelor of Science in Computer Science",
          "confidence": "MEDIUM",
          "provenance": {
            "source_type": "RESUME_PDF",
            "source_file": "data\\input\\resumes\\jane_doe_resume.pdf",
            "original_value": "Bachelor of Science in Computer Science",
            "transformation": null,
            "transformed_value": null,
            "timestamp": "2026-06-30T18:57:05.522781"
          }
        },
        "field_of_study": null,
        "graduation_date": {
          "value": "2017-06",
          "confidence": "MEDIUM",
          "provenance": {
            "source_type": "RESUME_PDF",
            "source_file": "data\\input\\resumes\\jane_doe_resume.pdf",
            "original_value": "2017",
            "transformation": "date_normalize",
            "transformed_value": "2017-06",
            "timestamp": "2026-06-30T18:57:05.526781"
          }
        }
      }
    ],
    "source_files": [
      "data\\input\\csv\\recruiter_export_1.csv",
      "data\\input\\resumes\\jane_doe_resume.pdf"
    ],
    "processing_timestamp": "2026-06-30T18:57:05.535341",
    "total_confidence": 0.8104,
    "merge_notes": [
      "Duplicate match: same normalized email.",
      "'name' agreed across CSV and resume; confidence boosted to HIGH.",
      "'skills' unioned from CSV (4) and resume (8) -> 8 unique.",
      "'job_titles' unioned from CSV (1) and resume (1) -> 1 unique.",
      "'current_company' agreed across CSV and resume; confidence boosted to HIGH.",
      "Conflict on 'years_of_experience': CSV='7.0' vs Resume='5.5' -> chose csv value."
    ],
    "current_company": {
      "value": "Google",
      "confidence": "HIGH",
      "provenance": {
        "source_type": "MERGED",
        "source_file": "merged",
        "original_value": [
          "Google",
          "Google"
        ],
        "transformation": "agreement_merge",
        "transformed_value": null,
        "timestamp": "2026-06-30T18:57:05.535326"
      }
    },
    "years_of_experience": {
      "value": 7.0,
      "confidence": "MEDIUM",
      "provenance": {
        "source_type": "MERGED",
        "source_file": "merged",
        "original_value": [
          7.0,
          5.5
        ],
        "transformation": "conflict_resolution:longest",
        "transformed_value": null,
        "timestamp": "2026-06-30T18:57:05.535335"
      }
    },
    "job_titles": [
      {
        "value": "Senior Software Engineer",
        "confidence": "HIGH",
        "provenance": {
          "source_type": "CSV",
          "source_file": "data\\input\\csv\\recruiter_export_1.csv",
          "original_value": "Senior Software Engineer",
          "transformation": null,
          "transformed_value": null,
          "timestamp": "2026-06-30T18:57:05.213573"
        }
      }
    ],
    "certifications": [
      {
        "value": "AWS Certified Solutions Architect",
        "confidence": "MEDIUM",
        "provenance": {
          "source_type": "RESUME_PDF",
          "source_file": "data\\input\\resumes\\jane_doe_resume.pdf",
          "original_value": "AWS Certified Solutions Architect",
          "transformation": null,
          "transformed_value": null,
          "timestamp": "2026-06-30T18:57:05.526833"
        }
      },
      {
        "value": "Certified Kubernetes Administrator",
        "confidence": "MEDIUM",
        "provenance": {
          "source_type": "RESUME_PDF",
          "source_file": "data\\input\\resumes\\jane_doe_resume.pdf",
          "original_value": "Certified Kubernetes Administrator",
          "transformation": null,
          "transformed_value": null,
          "timestamp": "2026-06-30T18:57:05.526836"
        }
      }
    ],
    "origin": "MERGED"
  },
  {
    "profile_id": "ec58b2f0-938a-455e-914f-b7f2060bc0f4",
    "name": {
      "value": "John Smith",
      "confidence": "HIGH",
      "provenance": {
        "source_type": "MERGED",
        "source_file": "merged",
        "original_value": [
          "John Smith",
          "John Smith"
        ],
        "transformation": "agreement_merge",
        "transformed_value": null,
        "timestamp": "2026-06-30T18:57:05.535354"
      }
    },
    "email": {
      "value": "john.smith@mail.com",
      "confidence": "HIGH",
      "provenance": {
        "source_type": "MERGED",
        "source_file": "merged",
        "original_value": [
          "john.smith@mail.com",
          "john.smith@mail.com"
        ],
        "transformation": "agreement_merge",
        "transformed_value": null,
        "timestamp": "2026-06-30T18:57:05.535356"
      }
    },
    "contact": {
      "email": {
        "value": "john.smith@mail.com",
        "confidence": "HIGH",
        "provenance": {
          "source_type": "MERGED",
          "source_file": "merged",
          "original_value": [
            "john.smith@mail.com",
            "john.smith@mail.com"
          ],
          "transformation": "agreement_merge",
          "transformed_value": null,
          "timestamp": "2026-06-30T18:57:05.535359"
        }
      },
      "phone": {
        "value": "+14155550199",
        "confidence": "HIGH",
        "provenance": {
          "source_type": "MERGED",
          "source_file": "merged",
          "original_value": [
            "+14155550199",
            "+14155550199"
          ],
          "transformation": "agreement_merge",
          "transformed_value": null,
          "timestamp": "2026-06-30T18:57:05.535360"
        }
      },
      "linkedin": {
        "value": "linkedin.com/in/johnsmith",
        "confidence": "HIGH",
        "provenance": {
          "source_type": "CSV",
          "source_file": "data\\input\\csv\\recruiter_export_1.csv",
          "original_value": "linkedin.com/in/johnsmith",
          "transformation": null,
          "transformed_value": null,
          "timestamp": "2026-06-30T18:57:05.214171"
        }
      },
      "address": null
    },
    "skills": [
      {
        "value": "Java",
        "confidence": "HIGH",
        "provenance": {
          "source_type": "CSV",
          "source_file": "data\\input\\csv\\recruiter_export_1.csv",
          "original_value": "Java",
          "transformation": null,
          "transformed_value": null,
          "timestamp": "2026-06-30T18:57:05.214176"
        }
      },
      {
        "value": "Spring Boot",
        "confidence": "HIGH",
        "provenance": {
          "source_type": "CSV",
          "source_file": "data\\input\\csv\\recruiter_export_1.csv",
          "original_value": "Spring Boot",
          "transformation": null,
          "transformed_value": null,
          "timestamp": "2026-06-30T18:57:05.214177"
        }
      },
      {
        "value": "Kubernetes",
        "confidence": "HIGH",
        "provenance": {
          "source_type": "CSV",
          "source_file": "data\\input\\csv\\recruiter_export_1.csv",
          "original_value": "Kubernetes",
          "transformation": null,
          "transformed_value": null,
          "timestamp": "2026-06-30T18:57:05.214178"
        }
      },
      {
        "value": "SQL",
        "confidence": "MEDIUM",
        "provenance": {
          "source_type": "RESUME_PDF",
          "source_file": "data\\input\\resumes\\john_smith_resume.pdf",
          "original_value": "SQL",
          "transformation": "taxonomy_map",
          "transformed_value": "SQL",
          "timestamp": "2026-06-30T18:57:05.285808"
        }
      },
      {
        "value": "Spring",
        "confidence": "MEDIUM",
        "provenance": {
          "source_type": "RESUME_PDF",
          "source_file": "data\\input\\resumes\\john_smith_resume.pdf",
          "original_value": "Spring",
          "transformation": "taxonomy_map",
          "transformed_value": "Spring",
          "timestamp": "2026-06-30T18:57:05.285809"
        }
      },
      {
        "value": "REST API",
        "confidence": "MEDIUM",
        "provenance": {
          "source_type": "RESUME_PDF",
          "source_file": "data\\input\\resumes\\john_smith_resume.pdf",
          "original_value": "REST API",
          "transformation": "taxonomy_map",
          "transformed_value": "REST API",
          "timestamp": "2026-06-30T18:57:05.285814"
        }
      },
      {
        "value": "Microservices",
        "confidence": "MEDIUM",
        "provenance": {
          "source_type": "RESUME_PDF",
          "source_file": "data\\input\\resumes\\john_smith_resume.pdf",
          "original_value": "Microservices",
          "transformation": "taxonomy_map",
          "transformed_value": "Microservices",
          "timestamp": "2026-06-30T18:57:05.285815"
        }
      },
      {
        "value": "Oracle",
        "confidence": "MEDIUM",
        "provenance": {
          "source_type": "RESUME_PDF",
          "source_file": "data\\input\\resumes\\john_smith_resume.pdf",
          "original_value": "Oracle",
          "transformation": "taxonomy_map",
          "transformed_value": "Oracle",
          "timestamp": "2026-06-30T18:57:05.285816"
        }
      }
    ],
    "experience": [
      {
        "company": {
          "value": "Amazon",
          "confidence": "MEDIUM",
          "provenance": {
            "source_type": "RESUME_PDF",
            "source_file": "data\\input\\resumes\\john_smith_resume.pdf",
            "original_value": "Amazon",
            "transformation": null,
            "transformed_value": null,
            "timestamp": "2026-06-30T18:57:05.522520"
          }
        },
        "title": {
          "value": "Backend Engineer",
          "confidence": "MEDIUM",
          "provenance": {
            "source_type": "RESUME_PDF",
            "source_file": "data\\input\\resumes\\john_smith_resume.pdf",
            "original_value": "Backend Engineer",
            "transformation": null,
            "transformed_value": null,
            "timestamp": "2026-06-30T18:57:05.522521"
          }
        },
        "start_date": {
          "value": "2019-03",
          "confidence": "MEDIUM",
          "provenance": {
            "source_type": "RESUME_PDF",
            "source_file": "data\\input\\resumes\\john_smith_resume.pdf",
            "original_value": "Mar 2019",
            "transformation": "date_normalize",
            "transformed_value": "2019-03",
            "timestamp": "2026-06-30T18:57:05.522513"
          }
        },
        "end_date": {
          "value": "PRESENT",
          "confidence": "MEDIUM",
          "provenance": {
            "source_type": "RESUME_PDF",
            "source_file": "data\\input\\resumes\\john_smith_resume.pdf",
            "original_value": "Present",
            "transformation": "date_normalize",
            "transformed_value": "PRESENT",
            "timestamp": "2026-06-30T18:57:05.522517"
          }
        },
        "description": {
          "value": "Mar 2019 - Present\nDesigned scalable REST APIs and microservices for fulfillment systems.\nSoftware Developer at Oracle\nJul 2015 - Feb 2019\nMaintained legacy Java applications and migrated to Spring Boot.",
          "confidence": "LOW",
          "provenance": {
            "source_type": "RESUME_PDF",
            "source_file": "data\\input\\resumes\\john_smith_resume.pdf",
            "original_value": "Mar 2019 - Present\nDesigned scalable REST APIs and microservices for fulfillment systems.\nSoftware Developer at Oracle\nJul 2015 - Feb 2019\nMaintained legacy Java applications and migrated to Spring Boot.",
            "transformation": null,
            "transformed_value": null,
            "timestamp": "2026-06-30T18:57:05.522523"
          }
        },
        "current": true
      }
    ],
    "education": [
      {
        "institution": {
          "value": "University of Michigan",
          "confidence": "MEDIUM",
          "provenance": {
            "source_type": "RESUME_PDF",
            "source_file": "data\\input\\resumes\\john_smith_resume.pdf",
            "original_value": "University of Michigan",
            "transformation": null,
            "transformed_value": null,
            "timestamp": "2026-06-30T18:57:05.522529"
          }
        },
        "degree": {
          "value": "Master of Science in Computer Science",
          "confidence": "MEDIUM",
          "provenance": {
            "source_type": "RESUME_PDF",
            "source_file": "data\\input\\resumes\\john_smith_resume.pdf",
            "original_value": "Master of Science in Computer Science",
            "transformation": null,
            "transformed_value": null,
            "timestamp": "2026-06-30T18:57:05.522531"
          }
        },
        "field_of_study": null,
        "graduation_date": {
          "value": "2015-06",
          "confidence": "MEDIUM",
          "provenance": {
            "source_type": "RESUME_PDF",
            "source_file": "data\\input\\resumes\\john_smith_resume.pdf",
            "original_value": "2015",
            "transformation": "date_normalize",
            "transformed_value": "2015-06",
            "timestamp": "2026-06-30T18:57:05.528743"
          }
        }
      }
    ],
    "source_files": [
      "data\\input\\csv\\recruiter_export_1.csv",
      "data\\input\\resumes\\john_smith_resume.pdf"
    ],
    "processing_timestamp": "2026-06-30T18:57:05.535386",
    "total_confidence": 0.7955,
    "merge_notes": [
      "Duplicate match: same normalized email.",
      "'name' agreed across CSV and resume; confidence boosted to HIGH.",
      "'skills' unioned from CSV (3) and resume (8) -> 8 unique.",
      "'job_titles' unioned from CSV (1) and resume (1) -> 1 unique.",
      "'current_company' agreed across CSV and resume; confidence boosted to HIGH.",
      "Conflict on 'years_of_experience': CSV='5.0' vs Resume='7.3' -> chose resume value."
    ],
    "current_company": {
      "value": "Amazon",
      "confidence": "HIGH",
      "provenance": {
        "source_type": "MERGED",
        "source_file": "merged",
        "original_value": [
          "Amazon",
          "Amazon"
        ],
        "transformation": "agreement_merge",
        "transformed_value": null,
        "timestamp": "2026-06-30T18:57:05.535376"
      }
    },
    "years_of_experience": {
      "value": 7.3,
      "confidence": "LOW",
      "provenance": {
        "source_type": "MERGED",
        "source_file": "merged",
        "original_value": [
          5.0,
          7.3
        ],
        "transformation": "conflict_resolution:longest",
        "transformed_value": null,
        "timestamp": "2026-06-30T18:57:05.535382"
      }
    },
    "job_titles": [
      {
        "value": "Backend Engineer",
        "confidence": "HIGH",
        "provenance": {
          "source_type": "CSV",
          "source_file": "data\\input\\csv\\recruiter_export_1.csv",
          "original_value": "Backend Engineer",
          "transformation": null,
          "transformed_value": null,
          "timestamp": "2026-06-30T18:57:05.214180"
        }
      }
    ],
    "certifications": [],
    "origin": "MERGED"
  },
  {
    "profile_id": "f298034e-c1b1-4f15-8cf7-f06587453a2b",
    "name": {
      "value": "Maria Garcia",
      "confidence": "HIGH",
      "provenance": {
        "source_type": "CSV",
        "source_file": "data\\input\\csv\\recruiter_export_1.csv",
        "original_value": "Maria Garcia",
        "transformation": null,
        "transformed_value": null,
        "timestamp": "2026-06-30T18:57:05.214399"
      }
    },
    "email": {
      "value": "maria.garcia@workmail.com",
      "confidence": "HIGH",
      "provenance": {
        "source_type": "CSV",
        "source_file": "data\\input\\csv\\recruiter_export_1.csv",
        "original_value": "maria.garcia@workmail.com",
        "transformation": "lowercase+trim",
        "transformed_value": "maria.garcia@workmail.com",
        "timestamp": "2026-06-30T18:57:05.214528"
      }
    },
    "contact": {
      "email": {
        "value": "maria.garcia@workmail.com",
        "confidence": "HIGH",
        "provenance": {
          "source_type": "CSV",
          "source_file": "data\\input\\csv\\recruiter_export_1.csv",
          "original_value": "maria.garcia@workmail.com",
          "transformation": "lowercase+trim",
          "transformed_value": "maria.garcia@workmail.com",
          "timestamp": "2026-06-30T18:57:05.214528"
        }
      },
      "phone": {
        "value": "+16505550143",
        "confidence": "HIGH",
        "provenance": {
          "source_type": "CSV",
          "source_file": "data\\input\\csv\\recruiter_export_1.csv",
          "original_value": "650-555-0143",
          "transformation": "E.164 normalize",
          "transformed_value": "+16505550143",
          "timestamp": "2026-06-30T18:57:05.214596"
        }
      },
      "linkedin": null,
      "address": null
    },
    "skills": [
      {
        "value": "React",
        "confidence": "HIGH",
        "provenance": {
          "source_type": "CSV",
          "source_file": "data\\input\\csv\\recruiter_export_1.csv",
          "original_value": "React",
          "transformation": null,
          "transformed_value": null,
          "timestamp": "2026-06-30T18:57:05.214643"
        }
      },
      {
        "value": "TypeScript",
        "confidence": "HIGH",
        "provenance": {
          "source_type": "CSV",
          "source_file": "data\\input\\csv\\recruiter_export_1.csv",
          "original_value": "TypeScript",
          "transformation": null,
          "transformed_value": null,
          "timestamp": "2026-06-30T18:57:05.214645"
        }
      },
      {
        "value": "Node.js",
        "confidence": "HIGH",
        "provenance": {
          "source_type": "CSV",
          "source_file": "data\\input\\csv\\recruiter_export_1.csv",
          "original_value": "Node.js",
          "transformation": null,
          "transformed_value": null,
          "timestamp": "2026-06-30T18:57:05.214646"
        }
      }
    ],
    "experience": [],
    "education": [],
    "source_files": [
      "data\\input\\csv\\recruiter_export_1.csv"
    ],
    "processing_timestamp": "2026-06-30T18:57:05.214668",
    "total_confidence": 1.0,
    "merge_notes": [],
    "current_company": {
      "value": "Meta",
      "confidence": "HIGH",
      "provenance": {
        "source_type": "CSV",
        "source_file": "data\\input\\csv\\recruiter_export_1.csv",
        "original_value": "Meta",
        "transformation": null,
        "transformed_value": null,
        "timestamp": "2026-06-30T18:57:05.214649"
      }
    },
    "years_of_experience": {
      "value": 4.0,
      "confidence": "HIGH",
      "provenance": {
        "source_type": "CSV",
        "source_file": "data\\input\\csv\\recruiter_export_1.csv",
        "original_value": "4",
        "transformation": "to_float",
        "transformed_value": 4.0,
        "timestamp": "2026-06-30T18:57:05.214652"
      }
    },
    "job_titles": [
      {
        "value": "Frontend Engineer",
        "confidence": "HIGH",
        "provenance": {
          "source_type": "CSV",
          "source_file": "data\\input\\csv\\recruiter_export_1.csv",
          "original_value": "Frontend Engineer",
          "transformation": null,
          "transformed_value": null,
          "timestamp": "2026-06-30T18:57:05.214647"
        }
      }
    ],
    "certifications": [],
    "origin": "CSV"
  },
  {
    "profile_id": "0c02b5c1-1d19-4589-9985-ebdf87b9779a",
    "name": {
      "value": "Alex Chen",
      "confidence": "HIGH",
      "provenance": {
        "source_type": "CSV",
        "source_file": "data\\input\\csv\\recruiter_export_1.csv",
        "original_value": "Alex Chen",
        "transformation": null,
        "transformed_value": null,
        "timestamp": "2026-06-30T18:57:05.214811"
      }
    },
    "email": {
      "value": "alex.chen@example.com",
      "confidence": "HIGH",
      "provenance": {
        "source_type": "CSV",
        "source_file": "data\\input\\csv\\recruiter_export_1.csv",
        "original_value": "alex.chen@example.com",
        "transformation": "lowercase+trim",
        "transformed_value": "alex.chen@example.com",
        "timestamp": "2026-06-30T18:57:05.214919"
      }
    },
    "contact": {
      "email": {
        "value": "alex.chen@example.com",
        "confidence": "HIGH",
        "provenance": {
          "source_type": "CSV",
          "source_file": "data\\input\\csv\\recruiter_export_1.csv",
          "original_value": "alex.chen@example.com",
          "transformation": "lowercase+trim",
          "transformed_value": "alex.chen@example.com",
          "timestamp": "2026-06-30T18:57:05.214919"
        }
      },
      "phone": {
        "value": "+12125550177",
        "confidence": "HIGH",
        "provenance": {
          "source_type": "CSV",
          "source_file": "data\\input\\csv\\recruiter_export_1.csv",
          "original_value": "212-555-0177",
          "transformation": "E.164 normalize",
          "transformed_value": "+12125550177",
          "timestamp": "2026-06-30T18:57:05.214975"
        }
      },
      "linkedin": {
        "value": "linkedin.com/in/alexchen",
        "confidence": "HIGH",
        "provenance": {
          "source_type": "CSV",
          "source_file": "data\\input\\csv\\recruiter_export_1.csv",
          "original_value": "linkedin.com/in/alexchen",
          "transformation": null,
          "transformed_value": null,
          "timestamp": "2026-06-30T18:57:05.215015"
        }
      },
      "address": null
    },
    "skills": [
      {
        "value": "SQL",
        "confidence": "HIGH",
        "provenance": {
          "source_type": "CSV",
          "source_file": "data\\input\\csv\\recruiter_export_1.csv",
          "original_value": "SQL",
          "transformation": null,
          "transformed_value": null,
          "timestamp": "2026-06-30T18:57:05.215019"
        }
      },
      {
        "value": "Tableau",
        "confidence": "HIGH",
        "provenance": {
          "source_type": "CSV",
          "source_file": "data\\input\\csv\\recruiter_export_1.csv",
          "original_value": "Tableau",
          "transformation": null,
          "transformed_value": null,
          "timestamp": "2026-06-30T18:57:05.215026"
        }
      },
      {
        "value": "Python",
        "confidence": "HIGH",
        "provenance": {
          "source_type": "CSV",
          "source_file": "data\\input\\csv\\recruiter_export_1.csv",
          "original_value": "Python",
          "transformation": null,
          "transformed_value": null,
          "timestamp": "2026-06-30T18:57:05.215027"
        }
      }
    ],
    "experience": [],
    "education": [],
    "source_files": [
      "data\\input\\csv\\recruiter_export_1.csv"
    ],
    "processing_timestamp": "2026-06-30T18:57:05.215047",
    "total_confidence": 1.0,
    "merge_notes": [],
    "current_company": {
      "value": "Microsoft",
      "confidence": "HIGH",
      "provenance": {
        "source_type": "CSV",
        "source_file": "data\\input\\csv\\recruiter_export_1.csv",
        "original_value": "Microsoft",
        "transformation": null,
        "transformed_value": null,
        "timestamp": "2026-06-30T18:57:05.215031"
      }
    },
    "years_of_experience": {
      "value": 3.0,
      "confidence": "HIGH",
      "provenance": {
        "source_type": "CSV",
        "source_file": "data\\input\\csv\\recruiter_export_1.csv",
        "original_value": "3",
        "transformation": "to_float",
        "transformed_value": 3.0,
        "timestamp": "2026-06-30T18:57:05.215033"
      }
    },
    "job_titles": [
      {
        "value": "Data Analyst",
        "confidence": "HIGH",
        "provenance": {
          "source_type": "CSV",
          "source_file": "data\\input\\csv\\recruiter_export_1.csv",
          "original_value": "Data Analyst",
          "transformation": null,
          "transformed_value": null,
          "timestamp": "2026-06-30T18:57:05.215029"
        }
      }
    ],
    "certifications": [],
    "origin": "CSV"
  },
  {
    "profile_id": "d4f15326-1940-4cb4-9506-ace41a292d22",
    "name": {
      "value": "Swathi S",
      "confidence": "HIGH",
      "provenance": {
        "source_type": "CSV",
        "source_file": "data\\input\\csv\\recruiter_export_3.csv",
        "original_value": "Swathi S",
        "transformation": null,
        "transformed_value": null,
        "timestamp": "2026-06-30T18:57:05.205385"
      }
    },
    "email": {
      "value": "swathirtcc27@gmail.com",
      "confidence": "HIGH",
      "provenance": {
        "source_type": "CSV",
        "source_file": "data\\input\\csv\\recruiter_export_3.csv",
        "original_value": "swathirtcc27@gmail.com",
        "transformation": "lowercase+trim",
        "transformed_value": "swathirtcc27@gmail.com",
        "timestamp": "2026-06-30T18:57:05.208697"
      }
    },
    "contact": {
      "email": {
        "value": "swathirtcc27@gmail.com",
        "confidence": "HIGH",
        "provenance": {
          "source_type": "CSV",
          "source_file": "data\\input\\csv\\recruiter_export_3.csv",
          "original_value": "swathirtcc27@gmail.com",
          "transformation": "lowercase+trim",
          "transformed_value": "swathirtcc27@gmail.com",
          "timestamp": "2026-06-30T18:57:05.208697"
        }
      },
      "phone": {
        "value": "+918072363364",
        "confidence": "HIGH",
        "provenance": {
          "source_type": "CSV",
          "source_file": "data\\input\\csv\\recruiter_export_3.csv",
          "original_value": "+91 8072363364",
          "transformation": "E.164 normalize",
          "transformed_value": "+918072363364",
          "timestamp": "2026-06-30T18:57:05.223029"
        }
      },
      "linkedin": {
        "value": "linkedin.com/in/swathi-s-cse",
        "confidence": "HIGH",
        "provenance": {
          "source_type": "CSV",
          "source_file": "data\\input\\csv\\recruiter_export_3.csv",
          "original_value": "linkedin.com/in/swathi-s-cse",
          "transformation": null,
          "transformed_value": null,
          "timestamp": "2026-06-30T18:57:05.223167"
        }
      },
      "address": null
    },
    "skills": [
      {
        "value": "Java",
        "confidence": "HIGH",
        "provenance": {
          "source_type": "CSV",
          "source_file": "data\\input\\csv\\recruiter_export_3.csv",
          "original_value": "Java",
          "transformation": null,
          "transformed_value": null,
          "timestamp": "2026-06-30T18:57:05.223194"
        }
      },
      {
        "value": "Python",
        "confidence": "HIGH",
        "provenance": {
          "source_type": "CSV",
          "source_file": "data\\input\\csv\\recruiter_export_3.csv",
          "original_value": "Python",
          "transformation": null,
          "transformed_value": null,
          "timestamp": "2026-06-30T18:57:05.223196"
        }
      },
      {
        "value": "Spring Boot",
        "confidence": "HIGH",
        "provenance": {
          "source_type": "CSV",
          "source_file": "data\\input\\csv\\recruiter_export_3.csv",
          "original_value": "Spring Boot",
          "transformation": null,
          "transformed_value": null,
          "timestamp": "2026-06-30T18:57:05.223197"
        }
      },
      {
        "value": "REST APIs",
        "confidence": "HIGH",
        "provenance": {
          "source_type": "CSV",
          "source_file": "data\\input\\csv\\recruiter_export_3.csv",
          "original_value": "REST APIs",
          "transformation": null,
          "transformed_value": null,
          "timestamp": "2026-06-30T18:57:05.223198"
        }
      },
      {
        "value": "MySQL",
        "confidence": "HIGH",
        "provenance": {
          "source_type": "CSV",
          "source_file": "data\\input\\csv\\recruiter_export_3.csv",
          "original_value": "MySQL",
          "transformation": null,
          "transformed_value": null,
          "timestamp": "2026-06-30T18:57:05.223199"
        }
      },
      {
        "value": "PostgreSQL",
        "confidence": "HIGH",
        "provenance": {
          "source_type": "CSV",
          "source_file": "data\\input\\csv\\recruiter_export_3.csv",
          "original_value": "PostgreSQL",
          "transformation": null,
          "transformed_value": null,
          "timestamp": "2026-06-30T18:57:05.223200"
        }
      },
      {
        "value": "AWS",
        "confidence": "HIGH",
        "provenance": {
          "source_type": "CSV",
          "source_file": "data\\input\\csv\\recruiter_export_3.csv",
          "original_value": "AWS",
          "transformation": null,
          "transformed_value": null,
          "timestamp": "2026-06-30T18:57:05.223201"
        }
      },
      {
        "value": "Git",
        "confidence": "HIGH",
        "provenance": {
          "source_type": "CSV",
          "source_file": "data\\input\\csv\\recruiter_export_3.csv",
          "original_value": "Git",
          "transformation": null,
          "transformed_value": null,
          "timestamp": "2026-06-30T18:57:05.223202"
        }
      },
      {
        "value": "GitHub",
        "confidence": "HIGH",
        "provenance": {
          "source_type": "CSV",
          "source_file": "data\\input\\csv\\recruiter_export_3.csv",
          "original_value": "GitHub",
          "transformation": null,
          "transformed_value": null,
          "timestamp": "2026-06-30T18:57:05.223203"
        }
      },
      {
        "value": "Network Security",
        "confidence": "HIGH",
        "provenance": {
          "source_type": "CSV",
          "source_file": "data\\input\\csv\\recruiter_export_3.csv",
          "original_value": "Network Security",
          "transformation": null,
          "transformed_value": null,
          "timestamp": "2026-06-30T18:57:05.223205"
        }
      },
      {
        "value": "VAPT",
        "confidence": "HIGH",
        "provenance": {
          "source_type": "CSV",
          "source_file": "data\\input\\csv\\recruiter_export_3.csv",
          "original_value": "VAPT",
          "transformation": null,
          "transformed_value": null,
          "timestamp": "2026-06-30T18:57:05.223205"
        }
      },
      {
        "value": "Web Application Security",
        "confidence": "HIGH",
        "provenance": {
          "source_type": "CSV",
          "source_file": "data\\input\\csv\\recruiter_export_3.csv",
          "original_value": "Web Application Security",
          "transformation": null,
          "transformed_value": null,
          "timestamp": "2026-06-30T18:57:05.223206"
        }
      },
      {
        "value": "React",
        "confidence": "HIGH",
        "provenance": {
          "source_type": "CSV",
          "source_file": "data\\input\\csv\\recruiter_export_3.csv",
          "original_value": "React",
          "transformation": null,
          "transformed_value": null,
          "timestamp": "2026-06-30T18:57:05.223207"
        }
      }
    ],
    "experience": [],
    "education": [],
    "source_files": [
      "data\\input\\csv\\recruiter_export_3.csv"
    ],
    "processing_timestamp": "2026-06-30T18:57:05.223252",
    "total_confidence": 1.0,
    "merge_notes": [],
    "current_company": {
      "value": "Internboot",
      "confidence": "HIGH",
      "provenance": {
        "source_type": "CSV",
        "source_file": "data\\input\\csv\\recruiter_export_3.csv",
        "original_value": "Internboot",
        "transformation": null,
        "transformed_value": null,
        "timestamp": "2026-06-30T18:57:05.223211"
      }
    },
    "years_of_experience": {
      "value": 0.5,
      "confidence": "HIGH",
      "provenance": {
        "source_type": "CSV",
        "source_file": "data\\input\\csv\\recruiter_export_3.csv",
        "original_value": "0.5",
        "transformation": "to_float",
        "transformed_value": 0.5,
        "timestamp": "2026-06-30T18:57:05.223216"
      }
    },
    "job_titles": [
      {
        "value": "Cybersecurity Intern",
        "confidence": "HIGH",
        "provenance": {
          "source_type": "CSV",
          "source_file": "data\\input\\csv\\recruiter_export_3.csv",
          "original_value": "Cybersecurity Intern",
          "transformation": null,
          "transformed_value": null,
          "timestamp": "2026-06-30T18:57:05.223209"
        }
      }
    ],
    "certifications": [],
    "origin": "CSV"
  },
  {
    "profile_id": "ad188cf9-82c0-44b4-81f7-21cb10063487",
    "name": {
      "value": "SWATHI S",
      "confidence": "MEDIUM",
      "provenance": {
        "source_type": "RESUME_PDF",
        "source_file": "data\\input\\resumes\\Swathi-S.pdf",
        "original_value": "SWATHI S",
        "transformation": null,
        "transformed_value": null,
        "timestamp": "2026-06-30T18:57:05.268394"
      }
    },
    "email": {
      "value": "",
      "confidence": "UNKNOWN",
      "provenance": {
        "source_type": "RESUME_PDF",
        "source_file": "data\\input\\resumes\\Swathi-S.pdf",
        "original_value": "",
        "transformation": null,
        "transformed_value": null,
        "timestamp": "2026-06-30T18:57:05.268403"
      }
    },
    "contact": {
      "email": {
        "value": "",
        "confidence": "UNKNOWN",
        "provenance": {
          "source_type": "RESUME_PDF",
          "source_file": "data\\input\\resumes\\Swathi-S.pdf",
          "original_value": "",
          "transformation": null,
          "transformed_value": null,
          "timestamp": "2026-06-30T18:57:05.268403"
        }
      },
      "phone": null,
      "linkedin": null,
      "address": null
    },
    "skills": [
      {
        "value": "AWS",
        "confidence": "MEDIUM",
        "provenance": {
          "source_type": "RESUME_PDF",
          "source_file": "data\\input\\resumes\\Swathi-S.pdf",
          "original_value": "AWS",
          "transformation": "taxonomy_map",
          "transformed_value": "AWS",
          "timestamp": "2026-06-30T18:57:05.268412"
        }
      }
    ],
    "experience": [],
    "education": [],
    "source_files": [
      "data\\input\\resumes\\Swathi-S.pdf"
    ],
    "processing_timestamp": "2026-06-30T18:57:05.268449",
    "total_confidence": 0.65,
    "merge_notes": [],
    "current_company": null,
    "years_of_experience": null,
    "job_titles": [],
    "certifications": [],
    "origin": "RESUME_PDF"
  },
  {
    "profile_id": "1727d054-500e-4ad2-bf99-125f9b4a6343",
    "name": {
      "value": "ABINEETH T",
      "confidence": "MEDIUM",
      "provenance": {
        "source_type": "RESUME_PDF",
        "source_file": "data\\input\\resumes\\Abineeth_T.pdf",
        "original_value": "ABINEETH T",
        "transformation": null,
        "transformed_value": null,
        "timestamp": "2026-06-30T18:57:05.465007"
      }
    },
    "email": {
      "value": "abineeththangavel@gmail.com",
      "confidence": "HIGH",
      "provenance": {
        "source_type": "RESUME_PDF",
        "source_file": "data\\input\\resumes\\Abineeth_T.pdf",
        "original_value": "abineeththangavel@gmail.com",
        "transformation": "lowercase+trim",
        "transformed_value": "abineeththangavel@gmail.com",
        "timestamp": "2026-06-30T18:57:05.465152"
      }
    },
    "contact": {
      "email": {
        "value": "abineeththangavel@gmail.com",
        "confidence": "HIGH",
        "provenance": {
          "source_type": "RESUME_PDF",
          "source_file": "data\\input\\resumes\\Abineeth_T.pdf",
          "original_value": "abineeththangavel@gmail.com",
          "transformation": "lowercase+trim",
          "transformed_value": "abineeththangavel@gmail.com",
          "timestamp": "2026-06-30T18:57:05.465152"
        }
      },
      "phone": {
        "value": "+919345646744",
        "confidence": "HIGH",
        "provenance": {
          "source_type": "RESUME_PDF",
          "source_file": "data\\input\\resumes\\Abineeth_T.pdf",
          "original_value": "+919345646744",
          "transformation": "E.164 normalize",
          "transformed_value": "+919345646744",
          "timestamp": "2026-06-30T18:57:05.465271"
        }
      },
      "linkedin": null,
      "address": null
    },
    "skills": [
      {
        "value": "Python",
        "confidence": "MEDIUM",
        "provenance": {
          "source_type": "RESUME_PDF",
          "source_file": "data\\input\\resumes\\Abineeth_T.pdf",
          "original_value": "Python",
          "transformation": "taxonomy_map",
          "transformed_value": "Python",
          "timestamp": "2026-06-30T18:57:05.465282"
        }
      },
      {
        "value": "Java",
        "confidence": "MEDIUM",
        "provenance": {
          "source_type": "RESUME_PDF",
          "source_file": "data\\input\\resumes\\Abineeth_T.pdf",
          "original_value": "Java",
          "transformation": "taxonomy_map",
          "transformed_value": "Java",
          "timestamp": "2026-06-30T18:57:05.465285"
        }
      },
      {
        "value": "Power BI",
        "confidence": "MEDIUM",
        "provenance": {
          "source_type": "RESUME_PDF",
          "source_file": "data\\input\\resumes\\Abineeth_T.pdf",
          "original_value": "Power BI",
          "transformation": "taxonomy_map",
          "transformed_value": "Power BI",
          "timestamp": "2026-06-30T18:57:05.465287"
        }
      },
      {
        "value": "Flask",
        "confidence": "MEDIUM",
        "provenance": {
          "source_type": "RESUME_PDF",
          "source_file": "data\\input\\resumes\\Abineeth_T.pdf",
          "original_value": "Flask",
          "transformation": "taxonomy_map",
          "transformed_value": "Flask",
          "timestamp": "2026-06-30T18:57:05.465288"
        }
      },
      {
        "value": "Pandas",
        "confidence": "MEDIUM",
        "provenance": {
          "source_type": "RESUME_PDF",
          "source_file": "data\\input\\resumes\\Abineeth_T.pdf",
          "original_value": "Pandas",
          "transformation": "taxonomy_map",
          "transformed_value": "Pandas",
          "timestamp": "2026-06-30T18:57:05.465290"
        }
      },
      {
        "value": "TensorFlow",
        "confidence": "MEDIUM",
        "provenance": {
          "source_type": "RESUME_PDF",
          "source_file": "data\\input\\resumes\\Abineeth_T.pdf",
          "original_value": "TensorFlow",
          "transformation": "taxonomy_map",
          "transformed_value": "TensorFlow",
          "timestamp": "2026-06-30T18:57:05.465291"
        }
      },
      {
        "value": "Scikit-learn",
        "confidence": "MEDIUM",
        "provenance": {
          "source_type": "RESUME_PDF",
          "source_file": "data\\input\\resumes\\Abineeth_T.pdf",
          "original_value": "Scikit-learn",
          "transformation": "taxonomy_map",
          "transformed_value": "Scikit-learn",
          "timestamp": "2026-06-30T18:57:05.465293"
        }
      }
    ],
    "experience": [],
    "education": [
      {
        "institution": {
          "value": "Sri Krishna Arts and Science College Jun 2023 - Apr 2026",
          "confidence": "MEDIUM",
          "provenance": {
            "source_type": "RESUME_PDF",
            "source_file": "data\\input\\resumes\\Abineeth_T.pdf",
            "original_value": "Sri Krishna Arts and Science College Jun 2023 - Apr 2026",
            "transformation": null,
            "transformed_value": null,
            "timestamp": "2026-06-30T18:57:05.465296"
          }
        },
        "degree": {
          "value": "Appin Technology, Coimbatore",
          "confidence": "MEDIUM",
          "provenance": {
            "source_type": "RESUME_PDF",
            "source_file": "data\\input\\resumes\\Abineeth_T.pdf",
            "original_value": "Appin Technology, Coimbatore",
            "transformation": null,
            "transformed_value": null,
            "timestamp": "2026-06-30T18:57:05.465297"
          }
        },
        "field_of_study": null,
        "graduation_date": {
          "value": "2023-06",
          "confidence": "MEDIUM",
          "provenance": {
            "source_type": "RESUME_PDF",
            "source_file": "data\\input\\resumes\\Abineeth_T.pdf",
            "original_value": "2023",
            "transformation": "date_normalize",
            "transformed_value": "2023-06",
            "timestamp": "2026-06-30T18:57:05.519681"
          }
        }
      }
    ],
    "source_files": [
      "data\\input\\resumes\\Abineeth_T.pdf"
    ],
    "processing_timestamp": "2026-06-30T18:57:05.519808",
    "total_confidence": 0.7308,
    "merge_notes": [],
    "current_company": null,
    "years_of_experience": null,
    "job_titles": [],
    "certifications": [],
    "origin": "RESUME_PDF"
  },
  {
    "profile_id": "c0c15c97-41ac-4bd3-beb1-a6aacef9fbd6",
    "name": {
      "value": "Wei Zhang",
      "confidence": "MEDIUM",
      "provenance": {
        "source_type": "RESUME_PDF",
        "source_file": "data\\input\\resumes\\wei_zhang_resume.pdf",
        "original_value": "Wei Zhang",
        "transformation": null,
        "transformed_value": null,
        "timestamp": "2026-06-30T18:57:05.302814"
      }
    },
    "email": {
      "value": "wei.zhang@example.com",
      "confidence": "HIGH",
      "provenance": {
        "source_type": "RESUME_PDF",
        "source_file": "data\\input\\resumes\\wei_zhang_resume.pdf",
        "original_value": "wei.zhang@example.com",
        "transformation": "lowercase+trim",
        "transformed_value": "wei.zhang@example.com",
        "timestamp": "2026-06-30T18:57:05.302948"
      }
    },
    "contact": {
      "email": {
        "value": "wei.zhang@example.com",
        "confidence": "HIGH",
        "provenance": {
          "source_type": "RESUME_PDF",
          "source_file": "data\\input\\resumes\\wei_zhang_resume.pdf",
          "original_value": "wei.zhang@example.com",
          "transformation": "lowercase+trim",
          "transformed_value": "wei.zhang@example.com",
          "timestamp": "2026-06-30T18:57:05.302948"
        }
      },
      "phone": {
        "value": "+12065550134",
        "confidence": "HIGH",
        "provenance": {
          "source_type": "RESUME_PDF",
          "source_file": "data\\input\\resumes\\wei_zhang_resume.pdf",
          "original_value": "(206) 555-0134",
          "transformation": "E.164 normalize",
          "transformed_value": "+12065550134",
          "timestamp": "2026-06-30T18:57:05.303073"
        }
      },
      "linkedin": null,
      "address": null
    },
    "skills": [
      {
        "value": "Python",
        "confidence": "MEDIUM",
        "provenance": {
          "source_type": "RESUME_PDF",
          "source_file": "data\\input\\resumes\\wei_zhang_resume.pdf",
          "original_value": "Python",
          "transformation": "taxonomy_map",
          "transformed_value": "Python",
          "timestamp": "2026-06-30T18:57:05.303082"
        }
      },
      {
        "value": "Pandas",
        "confidence": "MEDIUM",
        "provenance": {
          "source_type": "RESUME_PDF",
          "source_file": "data\\input\\resumes\\wei_zhang_resume.pdf",
          "original_value": "Pandas",
          "transformation": "taxonomy_map",
          "transformed_value": "Pandas",
          "timestamp": "2026-06-30T18:57:05.303085"
        }
      },
      {
        "value": "TensorFlow",
        "confidence": "MEDIUM",
        "provenance": {
          "source_type": "RESUME_PDF",
          "source_file": "data\\input\\resumes\\wei_zhang_resume.pdf",
          "original_value": "TensorFlow",
          "transformation": "taxonomy_map",
          "transformed_value": "TensorFlow",
          "timestamp": "2026-06-30T18:57:05.303086"
        }
      },
      {
        "value": "PyTorch",
        "confidence": "MEDIUM",
        "provenance": {
          "source_type": "RESUME_PDF",
          "source_file": "data\\input\\resumes\\wei_zhang_resume.pdf",
          "original_value": "PyTorch",
          "transformation": "taxonomy_map",
          "transformed_value": "PyTorch",
          "timestamp": "2026-06-30T18:57:05.303088"
        }
      },
      {
        "value": "Scikit-learn",
        "confidence": "MEDIUM",
        "provenance": {
          "source_type": "RESUME_PDF",
          "source_file": "data\\input\\resumes\\wei_zhang_resume.pdf",
          "original_value": "Scikit-learn",
          "transformation": "taxonomy_map",
          "transformed_value": "Scikit-learn",
          "timestamp": "2026-06-30T18:57:05.303089"
        }
      }
    ],
    "experience": [
      {
        "company": {
          "value": "Microsoft",
          "confidence": "MEDIUM",
          "provenance": {
            "source_type": "RESUME_PDF",
            "source_file": "data\\input\\resumes\\wei_zhang_resume.pdf",
            "original_value": "Microsoft",
            "transformation": null,
            "transformed_value": null,
            "timestamp": "2026-06-30T18:57:05.521623"
          }
        },
        "title": {
          "value": "Machine Learning Engineer",
          "confidence": "MEDIUM",
          "provenance": {
            "source_type": "RESUME_PDF",
            "source_file": "data\\input\\resumes\\wei_zhang_resume.pdf",
            "original_value": "Machine Learning Engineer",
            "transformation": null,
            "transformed_value": null,
            "timestamp": "2026-06-30T18:57:05.521626"
          }
        },
        "start_date": {
          "value": "2020-08",
          "confidence": "MEDIUM",
          "provenance": {
            "source_type": "RESUME_PDF",
            "source_file": "data\\input\\resumes\\wei_zhang_resume.pdf",
            "original_value": "Aug 2020",
            "transformation": "date_normalize",
            "transformed_value": "2020-08",
            "timestamp": "2026-06-30T18:57:05.521610"
          }
        },
        "end_date": {
          "value": "PRESENT",
          "confidence": "MEDIUM",
          "provenance": {
            "source_type": "RESUME_PDF",
            "source_file": "data\\input\\resumes\\wei_zhang_resume.pdf",
            "original_value": "Present",
            "transformation": "date_normalize",
            "transformed_value": "PRESENT",
            "timestamp": "2026-06-30T18:57:05.521620"
          }
        },
        "description": {
          "value": "Aug 2020 - Present\nBuilt recommendation models serving millions of users.",
          "confidence": "LOW",
          "provenance": {
            "source_type": "RESUME_PDF",
            "source_file": "data\\input\\resumes\\wei_zhang_resume.pdf",
            "original_value": "Aug 2020 - Present\nBuilt recommendation models serving millions of users.",
            "transformation": null,
            "transformed_value": null,
            "timestamp": "2026-06-30T18:57:05.521630"
          }
        },
        "current": true
      }
    ],
    "education": [
      {
        "institution": {
          "value": "Carnegie Mellon University",
          "confidence": "MEDIUM",
          "provenance": {
            "source_type": "RESUME_PDF",
            "source_file": "data\\input\\resumes\\wei_zhang_resume.pdf",
            "original_value": "Carnegie Mellon University",
            "transformation": null,
            "transformed_value": null,
            "timestamp": "2026-06-30T18:57:05.521641"
          }
        },
        "degree": {
          "value": "Master of Science, Machine Learning",
          "confidence": "MEDIUM",
          "provenance": {
            "source_type": "RESUME_PDF",
            "source_file": "data\\input\\resumes\\wei_zhang_resume.pdf",
            "original_value": "Master of Science, Machine Learning",
            "transformation": null,
            "transformed_value": null,
            "timestamp": "2026-06-30T18:57:05.521644"
          }
        },
        "field_of_study": null,
        "graduation_date": {
          "value": "2020-06",
          "confidence": "MEDIUM",
          "provenance": {
            "source_type": "RESUME_PDF",
            "source_file": "data\\input\\resumes\\wei_zhang_resume.pdf",
            "original_value": "2020",
            "transformation": "date_normalize",
            "transformed_value": "2020-06",
            "timestamp": "2026-06-30T18:57:05.527944"
          }
        }
      }
    ],
    "source_files": [
      "data\\input\\resumes\\wei_zhang_resume.pdf"
    ],
    "processing_timestamp": "2026-06-30T18:57:05.534238",
    "total_confidence": 0.6917,
    "merge_notes": [],
    "current_company": {
      "value": "Microsoft",
      "confidence": "MEDIUM",
      "provenance": {
        "source_type": "RESUME_PDF",
        "source_file": "data\\input\\resumes\\wei_zhang_resume.pdf",
        "original_value": "Microsoft",
        "transformation": null,
        "transformed_value": null,
        "timestamp": "2026-06-30T18:57:05.521623"
      }
    },
    "years_of_experience": {
      "value": 5.9,
      "confidence": "LOW",
      "provenance": {
        "source_type": "RESUME_PDF",
        "source_file": "data\\input\\resumes\\wei_zhang_resume.pdf",
        "original_value": 5.9,
        "transformation": "derived_from_date_ranges",
        "transformed_value": 5.9,
        "timestamp": "2026-06-30T18:57:05.534221"
      }
    },
    "job_titles": [
      {
        "value": "Machine Learning Engineer",
        "confidence": "MEDIUM",
        "provenance": {
          "source_type": "RESUME_PDF",
          "source_file": "data\\input\\resumes\\wei_zhang_resume.pdf",
          "original_value": "Machine Learning Engineer",
          "transformation": null,
          "transformed_value": null,
          "timestamp": "2026-06-30T18:57:05.521626"
        }
      }
    ],
    "certifications": [],
    "origin": "RESUME_PDF"
  }
]